param/__init__.py
param/api.py
param/enums.py
param/errors.py
param/manager.py
param/models.py
param/parameters.py
param/py.typed
param/resolvers.py
param/typing.py
param/utils.py
param/validation.py
param/wrappers.py
param/wrappers.pyi
tombulled_param-0.1.14.dist-info/LICENSE
tombulled_param-0.1.14.dist-info/WHEEL
tombulled_param-0.1.14.dist-info/METADATA
tombulled_param-0.1.14.dist-info/RECORD
