Metadata-Version: 2.1
Name: tombulled-param
Version: 0.1.14
Summary: Enhanced function parameters
Home-page: https://pypi.org/project/param/
License: MIT
Keywords: python,param
Author: Tom Bulled
Author-email: 26026015+tombulled@users.noreply.github.com
Requires-Python: >=3.8,<4.0
Classifier: License :: OSI Approved :: MIT License
Classifier: Programming Language :: Python :: 3
Classifier: Programming Language :: Python :: 3.8
Classifier: Programming Language :: Python :: 3.9
Classifier: Programming Language :: Python :: 3.10
Classifier: Programming Language :: Python :: 3.11
Requires-Dist: pydantic (>=1.10.2,<2.0.0)
Requires-Dist: roster (>=0.1.8,<0.2.0)
Project-URL: Repository, https://github.com/tombulled/param
